build/lib/build/lib/build/lib/build/lib/build/lib/build/lib/build/lib/peasyprofiller/__init__.py
build/lib/build/lib/build/lib/build/lib/build/lib/build/lib/build/lib/peasyprofiller/profiller.py
build/lib/build/lib/build/lib/build/lib/build/lib/build/lib/build/lib/peasyprofiller/tests/fibonacci.py
build/lib/build/lib/build/lib/build/lib/build/lib/build/lib/peasyprofiller/__init__.py
build/lib/build/lib/build/lib/build/lib/build/lib/build/lib/peasyprofiller/profiller.py
build/lib/build/lib/build/lib/build/lib/build/lib/build/lib/peasyprofiller/tests/fibonacci.py
build/lib/build/lib/build/lib/build/lib/build/lib/peasyprofiller/__init__.py
build/lib/build/lib/build/lib/build/lib/build/lib/peasyprofiller/profiller.py
build/lib/build/lib/build/lib/build/lib/build/lib/peasyprofiller/tests/fibonacci.py
build/lib/build/lib/build/lib/build/lib/peasyprofiller/__init__.py
build/lib/build/lib/build/lib/build/lib/peasyprofiller/profiller.py
build/lib/build/lib/build/lib/build/lib/peasyprofiller/tests/fibonacci.py
build/lib/build/lib/build/lib/peasyprofiller/__init__.py
build/lib/build/lib/build/lib/peasyprofiller/profiller.py
build/lib/build/lib/build/lib/peasyprofiller/tests/fibonacci.py
build/lib/build/lib/peasyprofiller/__init__.py
build/lib/build/lib/peasyprofiller/profiller.py
build/lib/build/lib/peasyprofiller/tests/fibonacci.py
build/lib/peasyprofiller/__init__.py
build/lib/peasyprofiller/profiller.py
build/lib/peasyprofiller/tests/fibonacci.py
peasyprofiller/__init__.py
peasyprofiller/profiller.py
peasyprofiller/tests/fibonacci.py
peasyprofiller-0.5.0.dist-info/LICENCE
peasyprofiller-0.5.0.dist-info/METADATA
peasyprofiller-0.5.0.dist-info/WHEEL
peasyprofiller-0.5.0.dist-info/top_level.txt
peasyprofiller-0.5.0.dist-info/RECORD
