Metadata-Version: 2.1
Name: peasyprofiller
Version: 0.5.0
Summary: Easy and simple profiller for Python
Home-page: https://github.com/moraguma/peasyprofiller
Author: Moraguma
Author-email: g170603@dac.unicamp.br
License: MIT
Classifier: Development Status :: 3 - Alpha
Classifier: Intended Audience :: Science/Research
Classifier: License :: OSI Approved :: MIT License
Classifier: Operating System :: POSIX :: Linux
Classifier: Programming Language :: Python
License-File: LICENCE
Requires-Dist: setuptools
Requires-Dist: matplotlib
Requires-Dist: numpy
